mgnify_pipelines_toolkit/__init__.py
mgnify_pipelines_toolkit/analysis/__init__.py
mgnify_pipelines_toolkit/analysis/amplicon/classify_var_regions.py
mgnify_pipelines_toolkit/analysis/amplicon/make_asv_count_table.py
mgnify_pipelines_toolkit/analysis/amplicon/mapseq_to_asv_table.py
mgnify_pipelines_toolkit/analysis/amplicon/permute_primers.py
mgnify_pipelines_toolkit/analysis/amplicon/primer_val_classification.py
mgnify_pipelines_toolkit/analysis/amplicon/remove_ambiguous_reads.py
mgnify_pipelines_toolkit/analysis/amplicon/rev_comp_se_primers.py
mgnify_pipelines_toolkit/analysis/amplicon/study_summary_generator.py
mgnify_pipelines_toolkit/analysis/assembly/add_rhea_chebi_annotation.py
mgnify_pipelines_toolkit/analysis/assembly/antismash_gff_builder.py
mgnify_pipelines_toolkit/analysis/assembly/combined_gene_caller_merge.py
mgnify_pipelines_toolkit/analysis/assembly/generate_gaf.py
mgnify_pipelines_toolkit/analysis/assembly/gff_annotation_utils.py
mgnify_pipelines_toolkit/analysis/assembly/gff_file_utils.py
mgnify_pipelines_toolkit/analysis/assembly/gff_toolkit.py
mgnify_pipelines_toolkit/analysis/assembly/go_utils.py
mgnify_pipelines_toolkit/analysis/assembly/krona_txt_from_cat_classification.py
mgnify_pipelines_toolkit/analysis/assembly/process_dbcan_result_cazys.py
mgnify_pipelines_toolkit/analysis/assembly/process_dbcan_result_clusters.py
mgnify_pipelines_toolkit/analysis/assembly/study_summary_generator.py
mgnify_pipelines_toolkit/analysis/assembly/summarise_antismash_bgcs.py
mgnify_pipelines_toolkit/analysis/assembly/summarise_goslims.py
mgnify_pipelines_toolkit/analysis/assembly/summarise_sanntis_bgcs.py
mgnify_pipelines_toolkit/analysis/genomes/__init__.py
mgnify_pipelines_toolkit/analysis/rawreads/study_summary_generator.py
mgnify_pipelines_toolkit/analysis/shared/__init__.py
mgnify_pipelines_toolkit/analysis/shared/amrintegrator.py
mgnify_pipelines_toolkit/analysis/shared/convert_cmscan_to_cmsearch_tblout.py
mgnify_pipelines_toolkit-1.4.12.dist-info/licenses/LICENSE
mgnify_pipelines_toolkit-1.4.12.dist-info/METADATA
mgnify_pipelines_toolkit-1.4.12.dist-info/WHEEL
mgnify_pipelines_toolkit-1.4.12.dist-info/entry_points.txt
mgnify_pipelines_toolkit-1.4.12.dist-info/top_level.txt
mgnify_pipelines_toolkit-1.4.12.dist-info/RECORD
