Metadata-Version: 2.4
Name: mgnify_pipelines_toolkit
Version: 1.4.12
Summary: Collection of scripts and tools for MGnify pipelines
Author-email: MGnify team <metagenomics-help@ebi.ac.uk>
License: Apache Software License 2.0
Keywords: bioinformatics,pipelines,metagenomics
Classifier: Programming Language :: Python :: 3
Classifier: License :: OSI Approved :: Apache Software License
Classifier: Operating System :: OS Independent
Requires-Python: >=3.11
License-File: LICENSE
Requires-Dist: biopython==1.85
Requires-Dist: pandas==2.2.3
Requires-Dist: pandera==0.27.1
Requires-Dist: pydantic<2.12.0
Requires-Dist: pyfastx==2.2.0
Requires-Dist: intervaltree==3.1.0
Requires-Dist: click~=8.1.8
Requires-Dist: requests~=2.32
Provides-Extra: test
Requires-Dist: pytest==8.3.5; extra == "test"
Requires-Dist: pytest-md==0.2.0; extra == "test"
Requires-Dist: pytest-workflow==2.1.0; extra == "test"
Provides-Extra: dev
Requires-Dist: pre-commit==4.2.0; extra == "dev"
Requires-Dist: black==25.1.0; extra == "dev"
Requires-Dist: ruff==0.8.4; extra == "dev"
Requires-Dist: isort==6.1.0; extra == "dev"
Dynamic: license-file
